rjdl/__init__.py
rjdl/console.py
rjdl/downloader.py
rjdl/objAlbum.py
rjdl/objMusic.py
rjdl/objPlaylist.py
rjdl/objPodcast.py
rjdl/objVideo.py
rjdl/search.py
rjdl-1.0.1.dist-info/LICENSE
rjdl-1.0.1.dist-info/METADATA
rjdl-1.0.1.dist-info/WHEEL
rjdl-1.0.1.dist-info/entry_points.txt
rjdl-1.0.1.dist-info/top_level.txt
rjdl-1.0.1.dist-info/RECORD
