Metadata-Version: 2.1
Name: rjdl
Version: 1.0.1
Summary: Download Music, Video, Album, Podcast & Playlists from www.RadioJavan.com
Home-page: https://github.com/reza00farjam/rjdl
Author: Reza Farjam
Author-email: reza.farjam78@gmail.com
License: MIT License
Platform: UNKNOWN
Classifier: Environment :: Console
Classifier: Programming Language :: Python :: 3
Classifier: License :: OSI Approved :: MIT License
Classifier: Operating System :: OS Independent
Requires-Python: >=3.6
License-File: LICENSE
Requires-Dist: requests (>=2.22.0)
Requires-Dist: beautifulsoup4 (>=4.9.1)
